Workbook

Sheet Raw Data
A1: Campaign_ID | B1: Campaign_Name | C1: Campaign_Type | D1: Platform | E1: Campaign_Start_Date | F1: Campaign_End_Date | G1: Region | H1: Audience_Segment | I1: Impressions | J1: Clicks | K1: CTR_Pct | L1: Leads_Generated | M1: Conversions | N1: Conversion_Rate_Pct | O1: Marketing_Spend | P1: Revenue_Generated | Q1: ROI_Pct | R1: CPC | S1: CPM | T1: CAC | U1: Campaign_Duration_Days | V1: Profit | W1: Month
A2: C001 | B2: Flash Sale Weekend | C2: Brand Awareness | D2: YouTube | E2: 2024-04-24 | F2: 2024-05-09 | G2: North | H2: 35-44 | I2: 307473 | J2: 5718 | K2: 1.86 | L2: 223 | M2: 170 | N2: 2.97 | O2: 138652.1 | P2: 183695.81 | Q2: 32.49 | R2: 24.25 | S2: 450.94 | T2: 815.6 | U2: 15 | V2: 45043.71 | W2: 2024-04
A3: C002 | B3: Cross-Sell Upsell | C3: Seasonal Sale | D3: Facebook | E3: 2024-04-11 | F3: 2024-05-22 | G3: Central | H3: 18-24 | I3: 189974 | J3: 6668 | K3: 3.51 | L3: 536 | M3: 238 | N3: 3.57 | O3: 34044.79 | P3: 50494.63 | Q3: 48.32 | R3: 5.11 | S3: 179.21 | T3: 143.05 | U3: 41 | V3: 16449.84 | W3: 2024-04
A4: C003 | B4: Retarget Lost Carts | C4: Retargeting | D4: LinkedIn | E4: 2024-06-21 | F4: 2024-07-04 | G4: East | H4: 25-34 | I4: 26078 | J4: 654 | K4: 2.51 | L4: 51 | M4: 31 | N4: 4.74 | O4: 134003.32 | P4: 382091.21 | Q4: 185.14 | R4: 204.9 | S4: 5138.56 | T4: 4322.69 | U4: 13 | V4: 248087.89 | W4: 2024-06
A5: C004 | B5: Cross-Sell Upsell | C5: Brand Awareness | D5: Email | E5: 2024-05-30 | F5: 2024-06-29 | G5: West | H5: 18-24 | I5: 47837 | J5: 7352 | K5: 15.37 | L5: 1013 | M5: 492 | N5: 6.69 | O5: 17292.79 | P5: 54520.06 | Q5: 215.28 | R5: 2.35 | S5: 361.49 | T5: 35.15 | U5: 30 | V5: 37227.27 | W5: 2024-05
A6: C005 | B6: Growth Hack Sprint | C6: Product Launch | D6: Google Ads | E6: 2024-03-24 | F6: 2024-04-23 | G6: East | H6: 45-54 | I6: 143132 | J6: 7457 | K6: 5.21 | L6: 623 | M6: 258 | N6: 3.46 | O6: 103519.58 | P6: 271629.98 | Q6: 162.39 | R6: 13.88 | S6: 723.25 | T6: 401.24 | U6: 30 | V6: 168110.4 | W6: 2024-03
A7: C006 | B7: LinkedIn B2B Push | C7: Lead Generation | D7: Email | E7: 2024-05-18 | F7: 2024-06-29 | G7: South | H7: 45-54 | I7: 24392 | J7: 5478 | K7: 22.46 | L7: 1744 | M7: 790 | N7: 14.42 | O7: 14114.66 | P7: 42797.2 | Q7: 203.21 | R7: 2.58 | S7: 578.66 | T7: 17.87 | U7: 42 | V7: 28682.54 | W7: 2024-05
A8: C007 | B8: Win-Back Campaign | C8: Retargeting | D8: LinkedIn | E8: 2024-06-10 | F8: 2024-06-30 | G8: North | H8: 25-34 | I8: 62954 | J8: 1731 | K8: 2.75 | L8: 260 | M8: 128 | N8: 7.39 | O8: 79227.32 | P8: 134045.18 | Q8: 69.19 | R8: 45.77 | S8: 1258.5 | T8: 618.96 | U8: 20 | V8: 54817.86 | W8: 2024-06
A9: C008 | B9: YouTube Pre-Roll | C9: Seasonal Sale | D9: Email | E9: 2024-10-25 | F9: 2024-11-26 | G9: East | H9: 55+ | I9: 33723 | J9: 5314 | K9: 15.76 | L9: 1581 | M9: 849 | N9: 15.98 | O9: 8794.25 | P9: 27848.29 | Q9: 216.66 | R9: 1.65 | S9: 260.78 | T9: 10.36 | U9: 32 | V9: 19054.04 | W9: 2024-10
A10: C009 | B10: Festive Season Blitz | C10: Lead Generation | D10: Facebook | E10: 2024-07-16 | F10: 2024-08-16 | G10: West | H10: 55+ | I10: 236208 | J10: 14148 | K10: 5.99 | L10: 1179 | M10: 479 | N10: 3.39 | O10: 33775.86 | P10: 46439.25 | Q10: 37.49 | R10: 2.39 | S10: 142.99 | T10: 70.51 | U10: 31 | V10: 12663.39 | W10: 2024-07
A11: C010 | B11: Loyalty Rewards Campaign | C11: Retargeting | D11: Email | E11: 2024-08-10 | F11: 2024-08-27 | G11: East | H11: 18-24 | I11: 39735 | J11: 5026 | K11: 12.65 | L11: 1418 | M11: 664 | N11: 13.21 | O11: 23645.71 | P11: 54821.07 | Q11: 131.84 | R11: 4.7 | S11: 595.09 | T11: 35.61 | U11: 17 | V11: 31175.36 | W11: 2024-08
A12: C011 | B12: Retarget Lost Carts | C12: Retargeting | D12: Google Ads | E12: 2024-03-19 | F12: 2024-04-18 | G12: Central | H12: 55+ | I12: 92349 | J12: 6270 | K12: 6.79 | L12: 651 | M12: 345 | N12: 5.5 | O12: 41660.04 | P12: 94678.84 | Q12: 127.27 | R12: 6.64 | S12: 451.12 | T12: 120.75 | U12: 30 | V12: 53018.8 | W12: 2024-03
A13: C012 | B13: Back to School Drive | C13: Retargeting | D13: Google Ads | E13: 2024-05-03 | F13: 2024-06-15 | G13: East | H13: 25-34 | I13: 70645 | J13: 3256 | K13: 4.61 | L13: 181 | M13: 141 | N13: 4.33 | O13: 141520.53 | P13: 198387.05 | Q13: 40.18 | R13: 43.46 | S13: 2003.26 | T13: 1003.69 | U13: 43 | V13: 56866.52 | W13: 2024-05
... A198: C200 | B198: Growth Hack Sprint | C198: Seasonal Sale | D198: LinkedIn | E198: 2024-08-22 | F198: 2024-09-09 | G198: North | H198: 35-44 | I198: 73329 | J198: 2273 | K198: 3.1 | L198: 380 | M198: 159 | N198: 7 | O198: 77188.71 | P198: 142926.15 | Q198: 85.16 | R198: 33.96 | S198: 1052.64 | T198: 485.46 | U198: 18 | V198: 65737.44 | W198: 2024-08

Sheet Summary KPIs
B2: 📊 Marketing Campaign Performance Dashboard — Summary KPIs
B3: Dataset: 197 Campaigns | Platforms: 6 | Period: Jan – Oct 2024
B5: 💰 Total Spend | D5: 📈 Total Revenue | F5: 🏆 Avg ROI % | H5: 🎯 Avg CTR %
B6: =SUM('Raw Data'!O2:O198) | D6: =SUM('Raw Data'!P2:P198) | F6: =AVERAGE('Raw Data'!Q2:Q198) | H6: =AVERAGE('Raw Data'!K2:K198)
B9: ✅ Total Conversions | D9: 📣 Impressions (M) | F9: 🧩 Total Leads | H9: 💵 Avg CAC (₹)
B10: =SUM('Raw Data'!M2:M198) | D10: =SUM('Raw Data'!I2:I198)/1000000 | F10: =SUM('Raw Data'!L2:L198) | H10: =AVERAGE('Raw Data'!T2:T198)
B14: Platform Performance Summary
B15: Platform | C15: Campaigns | D15: Avg ROI % | E15: Total Spend (₹) | F15: Total Revenue (₹) | G15: Avg CTR % | H15: Avg Conv Rate % | I15: Total Conversions | J15: Avg CAC (₹)
B16: YouTube | C16: 42 | D16: 117.83 | E16: 6585509.5 | F16: 14342854 | G16: 1.6 | H16: 2.4 | I16: 8831 | J16: 903.1
B17: LinkedIn | C17: 35 | D17: 107.33 | E17: 4660919.5 | F17: 9871488.8 | G17: 2.75 | H17: 5.66 | I17: 2857 | J17: 2175.26
B18: Google Ads | C18: 35 | D18: 114.26 | E18: 3117012.1 | F18: 6595582.4 | G18: 6.11 | H18: 4.72 | I18: 12544 | J18: 355.7
B19: Facebook | C19: 36 | D19: 125.12 | E19: 2668764.5 | F19: 5900722.5 | G19: 4.52 | H19: 3.24 | I19: 10297 | J19: 295.99
B20: Instagram | C20: 21 | D20: 121.15 | E20: 1257722.3 | F20: 2822431.5 | G20: 3.58 | H20: 2.94 | I20: 5169 | J20: 337.08
B21: Email | C21: 28 | D21: 155.2 | E21: 531717.11 | F21: 1341690.7 | G21: 19.41 | H21: 11.04 | I21: 17075 | J21: 39.11

Sheet Platform Analysis
A1: Platform Performance Analysis
A2: Platform | B2: Total Spend (₹) | C2: Total Revenue (₹) | D2: Avg ROI % | E2: Avg CTR % | F2: Avg CPC (₹) | G2: Total Conversions | H2: Avg CAC (₹)
A3: YouTube | B3: 6585509.5 | C3: 14342854 | D3: 117.83 | E3: 1.6 | F3: 20.16 | G3: 8831 | H3: 903.1
A4: LinkedIn | B4: 4660919.5 | C4: 9871488.8 | D4: 107.33 | E4: 2.75 | F4: 114.53 | G4: 2857 | H4: 2175.26
A5: Google Ads | B5: 3117012.1 | C5: 6595582.4 | D5: 114.26 | E5: 6.11 | F5: 15.72 | G5: 12544 | H5: 355.7
A6: Facebook | B6: 2668764.5 | C6: 5900722.5 | D6: 125.12 | E6: 4.52 | F6: 9.2 | G6: 10297 | H6: 295.99
A7: Instagram | B7: 1257722.3 | C7: 2822431.5 | D7: 121.15 | E7: 3.58 | F7: 9.13 | G7: 5169 | H7: 337.08
A8: Email | B8: 531717.11 | C8: 1341690.7 | D8: 155.2 | E8: 19.41 | F8: 4.18 | G8: 17075 | H8: 39.11

Sheet Region Analysis
A1: Regional Campaign Performance
A2: Region | B2: Campaigns | C2: Total Spend (₹) | D2: Total Revenue (₹) | E2: Avg ROI % | F2: Total Conversions | G2: Profit (₹)
A3: North | B3: 41 | C3: 3922359.5 | D3: 9643462.1 | E3: 139.27 | F3: 12773 | G3: 5721102.6
A4: Central | B4: 41 | C4: 3959661.9 | D4: 8787127.9 | E4: 122.28 | F4: 13082 | G4: 4827466.1
A5: South | B5: 41 | C5: 3982085.3 | D5: 8688250.2 | E5: 133.84 | F5: 11396 | G5: 4706164.9
A6: East | B6: 39 | C6: 3417085.1 | D6: 7099524.3 | E6: 113.93 | F6: 10346 | G6: 3682439.2
A7: West | B7: 35 | C7: 3540453.2 | D7: 6656405.5 | E7: 98.41 | F7: 9176 | G7: 3115952.3

Sheet Audience Analysis
A1: Audience Segment Performance Analysis
A2: Audience Segment | B2: Campaigns | C2: Avg ROI % | D2: Total Revenue (₹) | E2: Avg Conv Rate % | F2: Total Conversions | G2: Avg CAC (₹)
A3: 35-44 | B3: 42 | C3: 134.9 | D3: 8093474.6 | E3: 4.7 | F3: 13356 | G3: 531
A4: 18-24 | B4: 44 | C4: 129.89 | D4: 9453784.7 | E4: 5.21 | F4: 12672 | G4: 790.04
A5: 45-54 | B5: 41 | C5: 119.05 | D5: 9437726 | E5: 4.57 | F5: 12360 | G5: 768.48
A6: 55+ | B6: 33 | C6: 112.19 | D6: 5846687.3 | E6: 5.13 | F6: 9066 | G6: 799.91
A7: 25-34 | B7: 37 | C7: 111.74 | D7: 8043097.5 | E7: 4.56 | F7: 9319 | G7: 820.94

Sheet Monthly Trends
A1: Monthly Campaign Performance Trends
A2: Month | B2: Total Spend (₹) | C2: Total Revenue (₹) | D2: Avg ROI % | E2: Total Conversions | F2: Avg CTR % | G2: Campaigns
A3: 2024-01 | B3: 1634481.1 | C3: 3689780.6 | D3: 127.83 | E3: 5477 | F3: 6.84 | G3: 16
A4: 2024-02 | B4: 1653455.1 | C4: 3704909 | D4: 128.53 | E4: 4903 | F4: 5.38 | G4: 19
A5: 2024-03 | B5: 1685301.5 | C5: 3335855.6 | D5: 119.49 | E5: 3471 | F5: 4.21 | G5: 19
A6: 2024-04 | B6: 1619415.5 | C6: 3469181.7 | D6: 130.48 | E6: 7455 | F6: 8.38 | G6: 20
A7: 2024-05 | B7: 1954066.1 | C7: 3973203.1 | D7: 106.71 | E7: 5621 | F7: 5.61 | G7: 20
A8: 2024-06 | B8: 2751159.3 | C8: 5854435 | D8: 115.78 | E8: 4620 | F8: 3.72 | G8: 23
A9: 2024-07 | B9: 2284818.6 | C9: 5530662.3 | D9: 131.09 | E9: 6725 | F9: 4.52 | G9: 21
A10: 2024-08 | B10: 1680873.4 | C10: 3650130.8 | D10: 113.88 | E10: 6878 | F10: 8.32 | G10: 21
A11: 2024-09 | B11: 1527906.3 | C11: 3205355.6 | D11: 114.61 | E11: 5627 | F11: 6.42 | G11: 17
A12: 2024-10 | B12: 2030168.1 | C12: 4461256.5 | D12: 135.3 | E12: 5996 | F12: 5.83 | G12: 21
A13: TOTAL | B13: =SUM(B3:B12) | C13: =SUM(C3:C12) | D13: =AVERAGE(D3:D12) | E13: =SUM(E3:E12) | F13: =AVERAGE(F3:F12) | G13: =SUM(G3:G12)

Sheet Data Dictionary
A1: Data Dictionary — Marketing Campaign Performance Dataset
A2: Column Name | B2: Data Type | C2: Description | D2: Formula / Notes
A3: Campaign_ID | B3: Text | C3: Unique identifier for each campaign | D3: Generated: C001–C200
A4: Campaign_Name | B4: Text | C4: Descriptive name of the campaign | D4: From a list of 20 campaign names
A5: Campaign_Type | B5: Text | C5: Type: Brand Awareness / Lead Gen / Retargeting etc | D5: Categorical
A6: Platform | B6: Text | C6: Marketing platform used | D6: Google Ads, Facebook, Instagram, LinkedIn, Email, YouTube
A7: Campaign_Start_Date | B7: Date | C7: Start date of campaign | D7: YYYY-MM-DD format
A8: Campaign_End_Date | B8: Date | C8: End date of campaign | D8: YYYY-MM-DD format
A9: Region | B9: Text | C9: Geographic region | D9: North, South, East, West, Central
A10: Audience_Segment | B10: Text | C10: Age-based audience segment | D10: 18-24, 25-34, 35-44, 45-54, 55+
A11: Impressions | B11: Integer | C11: Total number of ad impressions | D11: Platform-specific realistic ranges
A12: Clicks | B12: Integer | C12: Total number of ad clicks | D12: =Impressions × CTR
A13: CTR_Pct | B13: Float | C13: Click-Through Rate percentage | D13: =(Clicks / Impressions) × 100
A14: Leads_Generated | B14: Integer | C14: Total leads captured by campaign | D14: =Conversions × 1.2–2.5 multiplier
A15: Conversions | B15: Integer | C15: Total conversions (purchases/sign-ups) | D15: =Clicks × Conversion Rate
A16: Conversion_Rate_Pct | B16: Float | C16: Conversion Rate percentage | D16: =(Conversions / Clicks) × 100
A17: Marketing_Spend | B17: Float | C17: Total money spent on campaign (₹) | D17: Platform-specific ranges
A18: Revenue_Generated | B18: Float | C18: Revenue attributed to campaign (₹) | D18: =Spend × Revenue Multiplier (1.1–3.5×)
A19: ROI_Pct | B19: Float | C19: Return on Investment percentage | D19: =((Revenue − Spend) / Spend) × 100
A20: CPC | B20: Float | C20: Cost Per Click (₹) | D20: =Marketing_Spend / Clicks
A21: CPM | B21: Float | C21: Cost Per Mille — per 1000 impressions (₹) | D21: =(Marketing_Spend / Impressions) × 1000
A22: CAC | B22: Float | C22: Customer Acquisition Cost (₹) | D22: =Marketing_Spend / Conversions
A23: Campaign_Duration_Days | B23: Integer | C23: Duration of campaign in days | D23: =End_Date − Start_Date
A24: Profit | B24: Float | C24: Gross profit from campaign (₹) | D24: =Revenue_Generated − Marketing_Spend
A25: Month | B25: Text | C25: Month of campaign start | D25: Extracted from Campaign_Start_Date (YYYY-MM)
